clave_unica_auth/__init__.py
clave_unica_auth/admin.py
clave_unica_auth/apps.py
clave_unica_auth/models.py
clave_unica_auth/settings.py
clave_unica_auth/tests.py
clave_unica_auth/urls.py
clave_unica_auth/views.py
clave_unica_auth/lib/utils/__init__.py
clave_unica_auth/lib/utils/oauth2_claveunica.py
clave_unica_auth/lib/utils/__pycache__/__init__.cpython-37.pyc
clave_unica_auth/lib/utils/__pycache__/oauth2_claveunica.cpython-37.pyc
clave_unica_auth/migrations/0001_initial.py
clave_unica_auth/migrations/0002_loginclaveunica_completed.py
clave_unica_auth/migrations/0003_loginclaveunica_user.py
clave_unica_auth/migrations/0004_auto_20190707_1720.py
clave_unica_auth/migrations/0005_auto_20190707_1738.py
clave_unica_auth/migrations/0006_auto_20190707_1808.py
clave_unica_auth/migrations/0007_auto_20190707_2110.py
clave_unica_auth/migrations/__init__.py
clave_unica_auth/templates/clave_unica_auth/error.html
django_clave_unica-1.0.1.dist-info/LICENSE
django_clave_unica-1.0.1.dist-info/METADATA
django_clave_unica-1.0.1.dist-info/WHEEL
django_clave_unica-1.0.1.dist-info/top_level.txt
django_clave_unica-1.0.1.dist-info/RECORD
