Metadata-Version: 2.1
Name: django-clave-unica
Version: 1.0.1
Summary: Aplicacion Django para integración con autenticación Clave Única
Home-page: https://github.com/GatoSnake
Author: Cristhian Won
Author-email: cristhian.won@gmail.com
License: BSD License
Platform: UNKNOWN
Classifier: Environment :: Web Environment
Classifier: Framework :: Django
Classifier: Framework :: Django :: 2.2
Classifier: Intended Audience :: Developers
Classifier: License :: OSI Approved :: BSD License
Classifier: Operating System :: OS Independent
Classifier: Programming Language :: Python
Classifier: Programming Language :: Python :: 3.5
Classifier: Programming Language :: Python :: 3.6
Classifier: Topic :: Internet :: WWW/HTTP
Classifier: Topic :: Internet :: WWW/HTTP :: Dynamic Content
Requires-Dist: requests (>=2.22.0)
Requires-Dist: urllib3 (>=1.25.3)
